LICENSE
MANIFEST.in
README.rst
setup.py
prettyexc/__init__.py
prettyexc/core.py
prettyexc/environment.py
prettyexc/exceptions.py
prettyexc/patch.py
prettyexc/tests.py
prettyexc/version.txt
tsl_prettyexc.egg-info/PKG-INFO
tsl_prettyexc.egg-info/SOURCES.txt
tsl_prettyexc.egg-info/dependency_links.txt
tsl_prettyexc.egg-info/requires.txt
tsl_prettyexc.egg-info/top_level.txt