Metadata-Version: 1.1
Name: tsl-prettyexc
Version: 0.5.2
Summary: Make any exception human readable in easy way.
Home-page: https://github.com/silverlogic/prettyexc
Author: Ryan Pineo
Author-email: ry@tsl.io
License: UNKNOWN
Platform: UNKNOWN
Classifier: Intended Audience :: Developers
Classifier: Operating System :: OS Independent
Classifier: Programming Language :: Python
Classifier: Programming Language :: Python :: 2
Classifier: Programming Language :: Python :: 2.6
Classifier: Programming Language :: Python :: 2.7
Classifier: Programming Language :: Python :: 3
Classifier: Programming Language :: Python :: 3.3
Classifier: Programming Language :: Python :: 3.4
